femap_neutral_parser/__init__.py
femap_neutral_parser/neutral_flavors.py
femap_neutral_parser/parser.py
femap_neutral_parser/utils.py
femap_neutral_parser/blocks/B100.py
femap_neutral_parser/blocks/B450.py
femap_neutral_parser/blocks/B451.py
femap_neutral_parser/blocks/__init__.py
femap_neutral_parser/blocks/_base.py
femap_neutral_parser/data/__init__.py
femap_neutral_parser/data/neutral_flavors.json
femap_neutral_parser-0.14.0.data/data/femap_neutral_parser/data/neutral_flavors.json
femap_neutral_parser-0.14.0.dist-info/AUTHORS.rst
femap_neutral_parser-0.14.0.dist-info/LICENSE
femap_neutral_parser-0.14.0.dist-info/METADATA
femap_neutral_parser-0.14.0.dist-info/WHEEL
femap_neutral_parser-0.14.0.dist-info/entry_points.txt
femap_neutral_parser-0.14.0.dist-info/top_level.txt
femap_neutral_parser-0.14.0.dist-info/RECORD
