Metadata-Version: 2.1
Name: femap-neutral-parser
Version: 0.14.0
Summary: FEMAP neutral file parser
Home-page: https://framagit.org/numenic/femap_neutral_parser
Author: Nicolas Cordier
Author-email: nicolas.cordier@numeric-gmbh.ch
License: MIT license
Keywords: femap_neutral_parser
Classifier: Development Status :: 2 - Pre-Alpha
Classifier: Intended Audience :: Developers
Classifier: License :: OSI Approved :: MIT License
Classifier: Natural Language :: English
Classifier: Programming Language :: Python :: 3.8
Classifier: Programming Language :: Python :: 3.9
Requires-Python: >=3.8
License-File: LICENSE
License-File: AUTHORS.rst
Requires-Dist: pandas
